Anr/__init__.py
Anr/main.py
anrk-0.1.1.dist-info/METADATA
anrk-0.1.1.dist-info/WHEEL
anrk-0.1.1.dist-info/entry_points.txt
anrk-0.1.1.dist-info/top_level.txt
anrk-0.1.1.dist-info/RECORD
